allcurrencyconverter/__init__.py
allcurrencyconverter/adapter.py
allcurrencyconverter/converter.py
allcurrencyconverter/enums.py
allcurrencyconverter/exceptions.py
allcurrencyconverter/httpwr.py
allcurrencyconverter/logging.py
allcurrencyconverter-0.1.0.dist-info/licenses/LICENSE
allcurrencyconverter-0.1.0.dist-info/METADATA
allcurrencyconverter-0.1.0.dist-info/WHEEL
allcurrencyconverter-0.1.0.dist-info/top_level.txt
allcurrencyconverter-0.1.0.dist-info/RECORD
