Metadata-Version: 2.4
Name: AllCurrencyConverter
Version: 0.1.0
Summary: PyPI package for converting a almost of currencies. Based on ExchangeRate-API (https://www.exchangerate-api.com)
Requires-Python: >=3.12
License-File: LICENSE
Requires-Dist: aiohttp[speedups]>=3.12.15
Requires-Dist: loguru>=0.7.3
Requires-Dist: pydantic>=2.11.7
Requires-Dist: typeguard>=4.4.4
Requires-Dist: uvloop
Provides-Extra: lint
Requires-Dist: ruff; extra == "lint"
Requires-Dist: pyright; extra == "lint"
Provides-Extra: test
Requires-Dist: pytest; extra == "test"
Requires-Dist: pytest-asyncio; extra == "test"
Requires-Dist: pytest-mock; extra == "test"
Requires-Dist: coverage[toml]; extra == "test"
Provides-Extra: profile
Requires-Dist: scalene; extra == "profile"
Provides-Extra: audit
Requires-Dist: pip-audit; extra == "audit"
Provides-Extra: dev
Requires-Dist: nox; extra == "dev"
Requires-Dist: commitizen; extra == "dev"
Requires-Dist: hatch; extra == "dev"
Provides-Extra: all
Requires-Dist: AllCurrencyConverter[lint]; extra == "all"
Requires-Dist: AllCurrencyConverter[test]; extra == "all"
Requires-Dist: AllCurrencyConverter[profile]; extra == "all"
Requires-Dist: AllCurrencyConverter[audit]; extra == "all"
Requires-Dist: AllCurrencyConverter[dev]; extra == "all"
Dynamic: license-file
